daily_hot_mcp/__init__.py
daily_hot_mcp/__main__.py
daily_hot_mcp/server.py
daily_hot_mcp/tooltypes.py
daily_hot_mcp/tools/__init__.py
daily_hot_mcp/tools/autohome.py
daily_hot_mcp/tools/baidu.py
daily_hot_mcp/tools/bbc.py
daily_hot_mcp/tools/bilibili.py
daily_hot_mcp/tools/crawlweb.py
daily_hot_mcp/tools/custom_rss.py
daily_hot_mcp/tools/douban.py
daily_hot_mcp/tools/douyin.py
daily_hot_mcp/tools/gcores.py
daily_hot_mcp/tools/hupu.py
daily_hot_mcp/tools/ifanr.py
daily_hot_mcp/tools/infoq.py
daily_hot_mcp/tools/ithome.py
daily_hot_mcp/tools/kr36.py
daily_hot_mcp/tools/kuaishou.py
daily_hot_mcp/tools/netease_news.py
daily_hot_mcp/tools/ninja_to5mac.py
daily_hot_mcp/tools/smzdm.py
daily_hot_mcp/tools/so360.py
daily_hot_mcp/tools/sogou.py
daily_hot_mcp/tools/sspai.py
daily_hot_mcp/tools/tencent_news.py
daily_hot_mcp/tools/thepaper.py
daily_hot_mcp/tools/theverge.py
daily_hot_mcp/tools/toutiao.py
daily_hot_mcp/tools/weibo.py
daily_hot_mcp/tools/weread.py
daily_hot_mcp/tools/xiaohongshu.py
daily_hot_mcp/tools/zhihu.py
daily_hot_mcp/utils/__init__.py
daily_hot_mcp/utils/cache.py
daily_hot_mcp/utils/http.py
daily_hot_mcp/utils/logger.py
daily_hot_mcp/utils/rss.py
daily_hot_mcp-1.6.7.dist-info/licenses/LICENSE
daily_hot_mcp-1.6.7.dist-info/METADATA
daily_hot_mcp-1.6.7.dist-info/WHEEL
daily_hot_mcp-1.6.7.dist-info/entry_points.txt
daily_hot_mcp-1.6.7.dist-info/top_level.txt
daily_hot_mcp-1.6.7.dist-info/RECORD
